{
  "acceptingDonations": false,
  "attribution": "",
  "attributionLink": "",
  "badgeText": "",
  "blurb": "",
  "category": "label",
  "displayCategory": "",
  "date": "01.09.2007",
  "description": "  ",
  "externalLinkText": "",
  "externalLinkUrl": "",
  "fixedPrice": "",
  "flexPriceMinimum": "",
  "flexPriceRecommended": "15",
  "hasFixedPrice": false,
  "id": 22,
  "isDigitalProduct": false,
  "published": true,
  "relatedContent": "",
  "relatedContentLink": "",
  "secondaryTitle": "Julia Holter",
  "slug": "eating-the-stars",
  "sticky": false,
  "tags": "record-releases",
  "title": "Eating the Stars",
  "titleWrapping": "",
  "trackSlug": "",
  "trackResourceId": "",
  "type": "Sample Pack for Ableton Live"
}