{
  "acceptingDonations": false,
  "attribution": "",
  "badgeText": "",
  "blurb": "",
  "date": "01.09.2007",
  "description": "  ",
  "fixedPrice": "",
  "flexPriceMinimum": "",
  "flexPriceRecommended": "15",
  "hasFixedPrice": false,
  "labelExternalLinkText": "",
  "labelExternalLinkUrl": "",
  "labelIsDigitalProduct": false,
  "published": true,
  "secondaryTitle": "",
  "slug": "hem-anniversary-one",
  "sticky": false,
  "tags": "label, events",
  "title": "HEM Anniversary One",
  "titleWrapping": "HEM Anni&shy;versary One",
  "trackId": "",
  "type": "Sample Pack for Ableton Live"
}