{
  "acceptingDonations": false,
  "attribution": "",
  "attributionLink": "",
  "badgeText": "",
  "blurb": "",
  "category": "list",
  "displayCategory": "",
  "date": "01.06.2020",
  "description": "compilation-iv\njason-gillis-grier\nseurat-standalone\nbreto",
  "externalLinkText": "",
  "externalLinkUrl": "",
  "fixedPrice": "",
  "flexPriceMinimum": "",
  "flexPriceRecommended": "",
  "hasFixedPrice": false,
  "id": 84,
  "isDigitalProduct": false,
  "published": true,
  "relatedContent": "",
  "relatedContentLink": "",
  "secondaryTitle": "",
  "slug": "home-page-features",
  "sticky": false,
  "tags": "",
  "title": "Home Page Features",
  "titleWrapping": "",
  "trackSlug": "",
  "trackResourceId": "",
  "trackResourceSecret": "",
  "type": ""
}