{
  "acceptingDonations": false,
  "attribution": "HEM Sound Library",
  "attributionLink": "/sound-library",
  "badgeText": "",
  "blurb": "",
  "category": "tracks",
  "displayCategory": "",
  "date": "01.09.2017",
  "description": "",
  "externalLinkText": "",
  "externalLinkUrl": "",
  "fixedPrice": "",
  "flexPriceMinimum": "",
  "flexPriceRecommended": "",
  "hasFixedPrice": false,
  "id": "",
  "isDigitalProduct": false,
  "published": false,
  "relatedContent": "mic-feedback",
  "relatedContentLink": "/sound-library/mic-feedback",
  "secondaryTitle": "",
  "slug": "mic-feedback-sample-track-5",
  "sticky": false,
  "tags": "attachment",
  "title": "Mic Feedback Sample Track 5",
  "titleWrapping": "",
  "trackSlug": "",
  "trackResourceId": "",
  "trackResourceSecret": "",
  "type": ""
}