{
  "acceptingDonations": false,
  "attribution": "",
  "attributionLink": "",
  "badgeText": "",
  "blurb": "",
  "date": "01.09.2013",
  "description": "  ",
  "externalLinkText": "Buy direct from artist",
  "externalLinkUrl": "asdfasf",
  "fixedPrice": "",
  "flexPriceMinimum": "",
  "flexPriceRecommended": "15",
  "hasFixedPrice": false,
  "isDigitalProduct": false,
  "published": true,
  "relatedContent": "",
  "relatedContentLink": "",
  "secondaryTitle": "Lucrecia Dalt",
  "slug": "syzygy",
  "sticky": false,
  "tags": "label, record-releases",
  "title": "Syzygy",
  "titleWrapping": "",
  "trackSlug": "",
  "trackResourceId": "",
  "type": "Sample Pack for Ableton Live"
}